irtm/__init__.py
irtm/toolbox.py
irtm-0.0.4.dist-info/LICENSE
irtm-0.0.4.dist-info/METADATA
irtm-0.0.4.dist-info/WHEEL
irtm-0.0.4.dist-info/top_level.txt
irtm-0.0.4.dist-info/RECORD
