Metadata-Version: 2.1
Name: irtm
Version: 0.0.4
Summary: A toolbox for Information Retrieval & Text Mining.
Home-page: https://github.com/KanishkNavale/IRTM-Toolbox.git
Author: Kanishk Navale
Author-email: navalekanishk@gmail.com
License: MIT
Platform: UNKNOWN
Classifier: Programming Language :: Python :: 3
Classifier: License :: OSI Approved :: MIT License
Classifier: Operating System :: OS Independent
Requires-Python: >=3.6
License-File: LICENSE
Requires-Dist: numpy
Requires-Dist: nltk
Requires-Dist: scikit-learn
